cat/__init__.py
cat/cli.py
cat/server.py
cat/shortcuts.py
cat/api/__init__.py
cat/api/coral_species.py
cat/api/file_projects.py
cat/data/reference/list_of_coral.csv
cat/docs/example_0.png
cat/docs/example_01.png
cat/docs/example_02.png
cat/docs/icon.ico
cat/docs/icon.png
cat/docs/logo.png
cat/docs/logo2.png
cat/docs/logo_wide.png
cat/scripts/__init__.py
cat/scripts/make_cog.py
cat/scripts/make_cog_batch.py
cat/web/annotation_file_mode.html
cat/web/converter.html
cat/web/index.html
cat/web/project_creator.html
coral_annotation_tool-1.0.29.dist-info/licenses/LICENSE.md
coral_annotation_tool-1.0.29.dist-info/METADATA
coral_annotation_tool-1.0.29.dist-info/WHEEL
coral_annotation_tool-1.0.29.dist-info/entry_points.txt
coral_annotation_tool-1.0.29.dist-info/top_level.txt
coral_annotation_tool-1.0.29.dist-info/RECORD
