Metadata-Version: 2.4
Name: coral-annotation-tool
Version: 1.0.29
Summary: CAT: Coral Annotation Tool. A file-based(JSON) Structure from Motion (SfM) orthomosaic annotation tool for coral reef research
Home-page: https://github.com/MichaelAkridge-NOAA/cat
Author: Michael Akridge
Author-email: 
License: MIT
Project-URL: Homepage, https://github.com/MichaelAkridge-NOAA/cat
Project-URL: Documentation, https://github.com/MichaelAkridge-NOAA/cat#readme
Project-URL: Repository, https://github.com/MichaelAkridge-NOAA/cat
Project-URL: Bug Tracker, https://github.com/MichaelAkridge-NOAA/cat/issues
Keywords: coral,annotation,geotiff,cog,orthomosaic,marine-biology,gis
Classifier: Development Status :: 4 - Beta
Classifier: Intended Audience :: Science/Research
Classifier: Topic :: Scientific/Engineering :: GIS
Classifier: Topic :: Scientific/Engineering :: Visualization
Classifier: Programming Language :: Python :: 3
Classifier: Programming Language :: Python :: 3.9
Classifier: Programming Language :: Python :: 3.10
Classifier: Programming Language :: Python :: 3.11
Classifier: Programming Language :: Python :: 3.12
Requires-Python: >=3.9
License-File: LICENSE.md
Requires-Dist: fastapi>=0.100.0
Requires-Dist: uvicorn[standard]>=0.23.0
Requires-Dist: titiler.core>=0.15.0
Requires-Dist: titiler.extensions>=0.15.0
Requires-Dist: rasterio>=1.3.0
Requires-Dist: rio-cogeo>=5.0.0
Requires-Dist: python-multipart>=0.0.6
Requires-Dist: aiofiles>=23.0.0
Requires-Dist: pydantic>=2.0.0
Requires-Dist: numpy>=1.24.0
Requires-Dist: geopandas>=0.14
Requires-Dist: pyogrio>=0.7
Requires-Dist: rtree>=1.0
Provides-Extra: dev
Requires-Dist: pytest>=7.0.0; extra == "dev"
Requires-Dist: pytest-asyncio>=0.21.0; extra == "dev"
Requires-Dist: black>=23.0.0; extra == "dev"
Requires-Dist: flake8>=6.0.0; extra == "dev"
Provides-Extra: shortcuts
Requires-Dist: pyshortcuts>=1.9.0; extra == "shortcuts"
Dynamic: home-page
Dynamic: license-file
Dynamic: requires-python
